<?xml version="1.0" encoding="utf-8"?>
<GraphData>
  <GraphID>3b79c940-8d15-4003-b60c-523db0bea158</GraphID>
  <Name>SG 00 TestGraph</Name>
  <Kommentar>Kommentar zu neuem Graph</Kommentar>
  <Erstellungsdatum>02/19/2019 11:55:01</Erstellungsdatum>
  <DefaultGraph>0</DefaultGraph>
  <Header>
    <InfoHeader>Copyright © Precitec GmbH &amp; Co. KG  2013</InfoHeader>
    <InfoUser></InfoUser>
    <GraphName>SG 00 TestGraph</GraphName>
    <GraphFileName>20190405_092257_SG 00 TestGraph.xml</GraphFileName>
    <Version Major="1" Minor="2" />
    <SicherungsDatum>04/05/2019 09:22:57</SicherungsDatum>
    <HeaderFilterInfoList>
      <HeaderFilterInfo>
        <FilterID>e40693d3-9e7f-4ba3-b3e1-a12d722efb41</FilterID>
        <FilterName>precitec::filter::PureResult</FilterName>
        <Version>Version 0.1.0</Version>
        <KomponenteID>4462301f-7abd-46fd-ac5b-c6dab54faa94</KomponenteID>
        <KomponenteAssemblyName>Filter_Results</KomponenteAssemblyName>
        <KomponenteErstellungsDatum>11/26/2018 10:21:50</KomponenteErstellungsDatum>
      </HeaderFilterInfo>
      <HeaderFilterInfo>
        <FilterID>e2ff0ec4-d2ce-47c3-8c92-9e2b1294c8ea</FilterID>
        <FilterName>precitec::filter::SampleSource</FilterName>
        <Version>Version 0.0.1</Version>
        <KomponenteID>5229d321-9bd9-4bb5-89ba-02bc1313b038</KomponenteID>
        <KomponenteAssemblyName>Filter_SampleSource</KomponenteAssemblyName>
        <KomponenteErstellungsDatum>11/26/2018 10:21:50</KomponenteErstellungsDatum>
      </HeaderFilterInfo>
      <HeaderFilterInfo>
        <FilterID>1a7f9c78-ff0a-4574-ad2d-a587f0561e13</FilterID>
        <FilterName>precitec::filter::ParameterFilter</FilterName>
        <Version>Version 0.0.2</Version>
        <KomponenteID>5e6df79f-39e2-4a9f-a76f-82e884afe0e9</KomponenteID>
        <KomponenteAssemblyName>Filter_Utility</KomponenteAssemblyName>
        <KomponenteErstellungsDatum>11/26/2018 10:21:50</KomponenteErstellungsDatum>
      </HeaderFilterInfo>
      <HeaderFilterInfo>
        <FilterID>e40693d3-9e7f-4ba3-b3e1-a12d722efb41</FilterID>
        <FilterName>precitec::filter::PureResult</FilterName>
        <Version>Version 0.1.0</Version>
        <KomponenteID>4462301f-7abd-46fd-ac5b-c6dab54faa94</KomponenteID>
        <KomponenteAssemblyName>Filter_Results</KomponenteAssemblyName>
        <KomponenteErstellungsDatum>11/26/2018 10:21:50</KomponenteErstellungsDatum>
      </HeaderFilterInfo>
      <HeaderFilterInfo>
        <FilterID>e2ff0ec4-d2ce-47c3-8c92-9e2b1294c8ea</FilterID>
        <FilterName>precitec::filter::SampleSource</FilterName>
        <Version>Version 0.0.1</Version>
        <KomponenteID>5229d321-9bd9-4bb5-89ba-02bc1313b038</KomponenteID>
        <KomponenteAssemblyName>Filter_SampleSource</KomponenteAssemblyName>
        <KomponenteErstellungsDatum>11/26/2018 10:21:50</KomponenteErstellungsDatum>
      </HeaderFilterInfo>
      <HeaderFilterInfo>
        <FilterID>caba9d15-30dd-4a0c-93e5-3000d68068f7</FilterID>
        <FilterName>precitec::filter::ImageSource</FilterName>
        <Version>Version 0.0.1</Version>
        <KomponenteID>609d64ff-0f63-4191-b5f2-b67e13116582</KomponenteID>
        <KomponenteAssemblyName>Filter_ImageSource</KomponenteAssemblyName>
        <KomponenteErstellungsDatum>11/26/2018 10:21:50</KomponenteErstellungsDatum>
      </HeaderFilterInfo>
      <HeaderFilterInfo>
        <FilterID>e40693d3-9e7f-4ba3-b3e1-a12d722efb41</FilterID>
        <FilterName>precitec::filter::PureResult</FilterName>
        <Version>Version 0.1.0</Version>
        <KomponenteID>4462301f-7abd-46fd-ac5b-c6dab54faa94</KomponenteID>
        <KomponenteAssemblyName>Filter_Results</KomponenteAssemblyName>
        <KomponenteErstellungsDatum>11/26/2018 10:21:50</KomponenteErstellungsDatum>
      </HeaderFilterInfo>
    </HeaderFilterInfoList>
  </Header>
  <ParameterSatzList>
    <ParameterSatz>
      <ParametersatzID>7c3c2d41-0d10-4af9-8a08-6063e8f3ddc4</ParametersatzID>
      <TypID>3b79c940-8d15-4003-b60c-523db0bea158</TypID>
      <ContentName>parametersatz.ContentName</ContentName>
      <ContentBeschreibung>parametersatz.ContentBeschreibung</ContentBeschreibung>
      <ContentTooltip>parametersatz.ContentTooltip</ContentTooltip>
      <TypName>Graph</TypName>
      <Name>Neuer Parametersatz</Name>
      <Beschreibung>Kommentar zu neuem Parametersatz</Beschreibung>
    </ParameterSatz>
  </ParameterSatzList>
  <InstanzFilterList>
    <InstanzFilter>
      <InstanzFilterID>6e96a6fd-d0f4-45e4-a6bd-50d9e597d34e</InstanzFilterID>
      <FilterID>e40693d3-9e7f-4ba3-b3e1-a12d722efb41</FilterID>
      <GraphID>3b79c940-8d15-4003-b60c-523db0bea158</GraphID>
      <Name>AnalogIN</Name>
      <InstanzFilterDescription PosX="450" PosY="260" Breite="80" Hoehe="80" />
      <InstanzFilterGrouping Group="-1" Parent="-1" GroupName="" />
    </InstanzFilter>
    <InstanzFilter>
      <InstanzFilterID>052ebb8b-ff13-42c4-aa67-5ef838cbebe5</InstanzFilterID>
      <FilterID>e2ff0ec4-d2ce-47c3-8c92-9e2b1294c8ea</FilterID>
      <GraphID>3b79c940-8d15-4003-b60c-523db0bea158</GraphID>
      <Name>ReadAnalogIn</Name>
      <InstanzFilterDescription PosX="90" PosY="260" Breite="80" Hoehe="80" />
      <InstanzFilterGrouping Group="-1" Parent="-1" GroupName="" />
    </InstanzFilter>
    <InstanzFilter>
      <InstanzFilterID>ac995174-05a1-4e42-8867-6c8d814b365c</InstanzFilterID>
      <FilterID>1a7f9c78-ff0a-4574-ad2d-a587f0561e13</FilterID>
      <GraphID>3b79c940-8d15-4003-b60c-523db0bea158</GraphID>
      <Name>send AnalogOUTvalue</Name>
      <InstanzFilterDescription PosX="310" PosY="100" Breite="80" Hoehe="80" />
      <InstanzFilterGrouping Group="-1" Parent="-1" GroupName="" />
    </InstanzFilter>
    <InstanzFilter>
      <InstanzFilterID>462ff9ba-2b27-4709-8dba-79b4f58c2f68</InstanzFilterID>
      <FilterID>e40693d3-9e7f-4ba3-b3e1-a12d722efb41</FilterID>
      <GraphID>3b79c940-8d15-4003-b60c-523db0bea158</GraphID>
      <Name>YaxisPos</Name>
      <InstanzFilterDescription PosX="450" PosY="410" Breite="80" Hoehe="80" />
      <InstanzFilterGrouping Group="-1" Parent="-1" GroupName="" />
    </InstanzFilter>
    <InstanzFilter>
      <InstanzFilterID>31f1550f-c4ef-442c-aa7c-b6be9a185068</InstanzFilterID>
      <FilterID>e2ff0ec4-d2ce-47c3-8c92-9e2b1294c8ea</FilterID>
      <GraphID>3b79c940-8d15-4003-b60c-523db0bea158</GraphID>
      <Name>ReadYW50pos</Name>
      <InstanzFilterDescription PosX="90" PosY="410" Breite="80" Hoehe="80" />
      <InstanzFilterGrouping Group="-1" Parent="-1" GroupName="" />
    </InstanzFilter>
    <InstanzFilter>
      <InstanzFilterID>5d06a3df-c309-4c54-af41-d86da52bbdb6</InstanzFilterID>
      <FilterID>caba9d15-30dd-4a0c-93e5-3000d68068f7</FilterID>
      <GraphID>3b79c940-8d15-4003-b60c-523db0bea158</GraphID>
      <Name>Bildquelle</Name>
      <InstanzFilterDescription PosX="90" PosY="100" Breite="80" Hoehe="80" />
      <InstanzFilterGrouping Group="-1" Parent="-1" GroupName="" />
    </InstanzFilter>
    <InstanzFilter>
      <InstanzFilterID>617145b9-ec00-4020-bc56-f78cad73e736</InstanzFilterID>
      <FilterID>e40693d3-9e7f-4ba3-b3e1-a12d722efb41</FilterID>
      <GraphID>3b79c940-8d15-4003-b60c-523db0bea158</GraphID>
      <Name>AnalogOUT</Name>
      <InstanzFilterDescription PosX="450" PosY="100" Breite="80" Hoehe="80" />
      <InstanzFilterGrouping Group="-1" Parent="-1" GroupName="" />
    </InstanzFilter>
  </InstanzFilterList>
  <InstanzPipeList>
    <InstanzPipe>
      <InstanzPipeID>d42d71fc-74a7-4309-9ff6-ec3df686012e</InstanzPipeID>
      <PipePath>M172.64,275.4L447.36,275.4</PipePath>
      <ReceiverConnectorID>33e1c20b-1f4d-46b5-bf11-188c5d6aadb6</ReceiverConnectorID>
      <ReceiverConnectorName></ReceiverConnectorName>
      <ReceiverConnectorGroup>0</ReceiverConnectorGroup>
      <ReceiverInstFilterID>6e96a6fd-d0f4-45e4-a6bd-50d9e597d34e</ReceiverInstFilterID>
      <SenderConnectorID>bf863352-f08c-46f8-a356-7aaa88af0bc0</SenderConnectorID>
      <SenderConnectorName>SampleFrame</SenderConnectorName>
      <SenderInstFilterID>052ebb8b-ff13-42c4-aa67-5ef838cbebe5</SenderInstFilterID>
    </InstanzPipe>
    <InstanzPipe>
      <InstanzPipeID>e72ac443-36ed-4f8a-92a3-4aa1cd7831cb</InstanzPipeID>
      <PipePath>M172.64,115.4L307.36,115.4</PipePath>
      <ReceiverConnectorID>b1fc92b7-be22-4765-b202-45fd88d6c2ce</ReceiverConnectorID>
      <ReceiverConnectorName></ReceiverConnectorName>
      <ReceiverConnectorGroup>0</ReceiverConnectorGroup>
      <ReceiverInstFilterID>ac995174-05a1-4e42-8867-6c8d814b365c</ReceiverInstFilterID>
      <SenderConnectorID>eba8f843-6403-4e02-9000-bf68c946783e</SenderConnectorID>
      <SenderConnectorName>ImageFrame</SenderConnectorName>
      <SenderInstFilterID>5d06a3df-c309-4c54-af41-d86da52bbdb6</SenderInstFilterID>
    </InstanzPipe>
    <InstanzPipe>
      <InstanzPipeID>bcf3833f-44a7-425a-9fa6-eb9fcb334cd4</InstanzPipeID>
      <PipePath>M172.64,425.4L447.36,425.4</PipePath>
      <ReceiverConnectorID>33e1c20b-1f4d-46b5-bf11-188c5d6aadb6</ReceiverConnectorID>
      <ReceiverConnectorName></ReceiverConnectorName>
      <ReceiverConnectorGroup>0</ReceiverConnectorGroup>
      <ReceiverInstFilterID>462ff9ba-2b27-4709-8dba-79b4f58c2f68</ReceiverInstFilterID>
      <SenderConnectorID>bf863352-f08c-46f8-a356-7aaa88af0bc0</SenderConnectorID>
      <SenderConnectorName>SampleFrame</SenderConnectorName>
      <SenderInstFilterID>31f1550f-c4ef-442c-aa7c-b6be9a185068</SenderInstFilterID>
    </InstanzPipe>
    <InstanzPipe>
      <InstanzPipeID>a3e9e714-38aa-4fe2-8180-12e0dfa73667</InstanzPipeID>
      <PipePath>M392.64,115.4L447.36,115.4</PipePath>
      <ReceiverConnectorID>33e1c20b-1f4d-46b5-bf11-188c5d6aadb6</ReceiverConnectorID>
      <ReceiverConnectorName></ReceiverConnectorName>
      <ReceiverConnectorGroup>0</ReceiverConnectorGroup>
      <ReceiverInstFilterID>617145b9-ec00-4020-bc56-f78cad73e736</ReceiverInstFilterID>
      <SenderConnectorID>2495a1d1-6022-48c8-9b56-6e6ca2d67d88</SenderConnectorID>
      <SenderConnectorName>Scalar</SenderConnectorName>
      <SenderInstFilterID>ac995174-05a1-4e42-8867-6c8d814b365c</SenderInstFilterID>
    </InstanzPipe>
  </InstanzPipeList>
  <InstanzVariantList>
    <InstanzVariant>
      <InstanzVariantID>aa3ee3d9-bf02-45fe-9e69-0c217f54b413</InstanzVariantID>
      <ParentID>00000000-0000-0000-0000-000000000000</ParentID>
      <VariantID>1d788750-1ba4-457e-b1aa-759b473a236c</VariantID>
      <ParametersatzID>7c3c2d41-0d10-4af9-8a08-6063e8f3ddc4</ParametersatzID>
      <InstanceFilterID>6e96a6fd-d0f4-45e4-a6bd-50d9e597d34e</InstanceFilterID>
      <HardwareKonfigID>00000000-0000-0000-0000-000000000000</HardwareKonfigID>
      <StationID>00000000-0000-0000-0000-000000000000</StationID>
      <ProduktID>00000000-0000-0000-0000-000000000000</ProduktID>
      <EditListOrder />
      <Name></Name>
    </InstanzVariant>
    <InstanzVariant>
      <InstanzVariantID>ecb8f0e3-5da6-41b7-8abc-6b0fbf3f2aa4</InstanzVariantID>
      <ParentID>00000000-0000-0000-0000-000000000000</ParentID>
      <VariantID>7005ffb6-246b-495d-be40-a50fccdf5e91</VariantID>
      <ParametersatzID>7c3c2d41-0d10-4af9-8a08-6063e8f3ddc4</ParametersatzID>
      <InstanceFilterID>052ebb8b-ff13-42c4-aa67-5ef838cbebe5</InstanceFilterID>
      <HardwareKonfigID>00000000-0000-0000-0000-000000000000</HardwareKonfigID>
      <StationID>00000000-0000-0000-0000-000000000000</StationID>
      <ProduktID>00000000-0000-0000-0000-000000000000</ProduktID>
      <EditListOrder />
      <Name></Name>
    </InstanzVariant>
    <InstanzVariant>
      <InstanzVariantID>dbf58fde-5bd6-4d53-bb02-47eb5205b0db</InstanzVariantID>
      <ParentID>00000000-0000-0000-0000-000000000000</ParentID>
      <VariantID>7bc89cb7-48e0-4c94-9f6a-0f5f7fdbeeba</VariantID>
      <ParametersatzID>7c3c2d41-0d10-4af9-8a08-6063e8f3ddc4</ParametersatzID>
      <InstanceFilterID>ac995174-05a1-4e42-8867-6c8d814b365c</InstanceFilterID>
      <HardwareKonfigID>00000000-0000-0000-0000-000000000000</HardwareKonfigID>
      <StationID>00000000-0000-0000-0000-000000000000</StationID>
      <ProduktID>00000000-0000-0000-0000-000000000000</ProduktID>
      <EditListOrder />
      <Name></Name>
    </InstanzVariant>
    <InstanzVariant>
      <InstanzVariantID>bb0406fd-3918-46a8-9825-911b22f22f39</InstanzVariantID>
      <ParentID>00000000-0000-0000-0000-000000000000</ParentID>
      <VariantID>1d788750-1ba4-457e-b1aa-759b473a236c</VariantID>
      <ParametersatzID>7c3c2d41-0d10-4af9-8a08-6063e8f3ddc4</ParametersatzID>
      <InstanceFilterID>462ff9ba-2b27-4709-8dba-79b4f58c2f68</InstanceFilterID>
      <HardwareKonfigID>00000000-0000-0000-0000-000000000000</HardwareKonfigID>
      <StationID>00000000-0000-0000-0000-000000000000</StationID>
      <ProduktID>00000000-0000-0000-0000-000000000000</ProduktID>
      <EditListOrder />
      <Name></Name>
    </InstanzVariant>
    <InstanzVariant>
      <InstanzVariantID>18c68746-3327-4732-906d-676ef71b58d3</InstanzVariantID>
      <ParentID>00000000-0000-0000-0000-000000000000</ParentID>
      <VariantID>7005ffb6-246b-495d-be40-a50fccdf5e91</VariantID>
      <ParametersatzID>7c3c2d41-0d10-4af9-8a08-6063e8f3ddc4</ParametersatzID>
      <InstanceFilterID>31f1550f-c4ef-442c-aa7c-b6be9a185068</InstanceFilterID>
      <HardwareKonfigID>00000000-0000-0000-0000-000000000000</HardwareKonfigID>
      <StationID>00000000-0000-0000-0000-000000000000</StationID>
      <ProduktID>00000000-0000-0000-0000-000000000000</ProduktID>
      <EditListOrder />
      <Name></Name>
    </InstanzVariant>
    <InstanzVariant>
      <InstanzVariantID>1a32995a-aec8-45c6-80a9-d8f0364f00c6</InstanzVariantID>
      <ParentID>00000000-0000-0000-0000-000000000000</ParentID>
      <VariantID>52477129-33ee-4bad-a3dc-0b8ac907ebad</VariantID>
      <ParametersatzID>7c3c2d41-0d10-4af9-8a08-6063e8f3ddc4</ParametersatzID>
      <InstanceFilterID>5d06a3df-c309-4c54-af41-d86da52bbdb6</InstanceFilterID>
      <HardwareKonfigID>00000000-0000-0000-0000-000000000000</HardwareKonfigID>
      <StationID>00000000-0000-0000-0000-000000000000</StationID>
      <ProduktID>00000000-0000-0000-0000-000000000000</ProduktID>
      <EditListOrder />
      <Name></Name>
    </InstanzVariant>
    <InstanzVariant>
      <InstanzVariantID>cd0e46e2-093b-400a-8047-1b98094976e6</InstanzVariantID>
      <ParentID>00000000-0000-0000-0000-000000000000</ParentID>
      <VariantID>1d788750-1ba4-457e-b1aa-759b473a236c</VariantID>
      <ParametersatzID>7c3c2d41-0d10-4af9-8a08-6063e8f3ddc4</ParametersatzID>
      <InstanceFilterID>617145b9-ec00-4020-bc56-f78cad73e736</InstanceFilterID>
      <HardwareKonfigID>00000000-0000-0000-0000-000000000000</HardwareKonfigID>
      <StationID>00000000-0000-0000-0000-000000000000</StationID>
      <ProduktID>00000000-0000-0000-0000-000000000000</ProduktID>
      <EditListOrder />
      <Name></Name>
    </InstanzVariant>
  </InstanzVariantList>
  <InstanzAttributeList>
    <InstanzAttribute>
      <InstanzAttributeID>c70c0ec5-e3bc-4da8-a433-6bd901973ef8</InstanzAttributeID>
      <InstanzVariantID>aa3ee3d9-bf02-45fe-9e69-0c217f54b413</InstanzVariantID>
      <VariantID>1d788750-1ba4-457e-b1aa-759b473a236c</VariantID>
      <InstanceFilterID>6e96a6fd-d0f4-45e4-a6bd-50d9e597d34e</InstanceFilterID>
      <AttributeID>1bab875b-3599-4c75-bb75-e3640dfc7c74</AttributeID>
      <AttributeName>Verbosity</AttributeName>
      <UserLevel>0</UserLevel>
      <Visible>true</Visible>
      <Value>0</Value>
      <Blob>1</Blob>
      <Publicity>true</Publicity>
    </InstanzAttribute>
    <InstanzAttribute>
      <InstanzAttributeID>8c0105d5-98c7-4f91-8c95-7d08ee3b80de</InstanzAttributeID>
      <InstanzVariantID>aa3ee3d9-bf02-45fe-9e69-0c217f54b413</InstanzVariantID>
      <VariantID>1d788750-1ba4-457e-b1aa-759b473a236c</VariantID>
      <InstanceFilterID>6e96a6fd-d0f4-45e4-a6bd-50d9e597d34e</InstanceFilterID>
      <AttributeID>8b47f3a6-bb10-4384-b7de-b1b4cb60e510</AttributeID>
      <AttributeName>ResultType</AttributeName>
      <UserLevel>0</UserLevel>
      <Visible>true</Visible>
      <Value>509</Value>
      <Blob>-1</Blob>
      <Publicity>true</Publicity>
    </InstanzAttribute>
    <InstanzAttribute>
      <InstanzAttributeID>04b4b068-7ab5-4fe0-9ee5-04edd6a21324</InstanzAttributeID>
      <InstanzVariantID>ecb8f0e3-5da6-41b7-8abc-6b0fbf3f2aa4</InstanzVariantID>
      <VariantID>7005ffb6-246b-495d-be40-a50fccdf5e91</VariantID>
      <InstanceFilterID>052ebb8b-ff13-42c4-aa67-5ef838cbebe5</InstanceFilterID>
      <AttributeID>39e944dd-f2a0-4ae3-8854-f200c4ca8455</AttributeID>
      <AttributeName>sensorid</AttributeName>
      <UserLevel>0</UserLevel>
      <Visible>true</Visible>
      <Value>10027</Value>
      <Blob>10000</Blob>
      <Publicity>true</Publicity>
    </InstanzAttribute>
    <InstanzAttribute>
      <InstanzAttributeID>3cb0c2c7-e999-4b98-a32b-0bbe1311752b</InstanzAttributeID>
      <InstanzVariantID>ecb8f0e3-5da6-41b7-8abc-6b0fbf3f2aa4</InstanzVariantID>
      <VariantID>7005ffb6-246b-495d-be40-a50fccdf5e91</VariantID>
      <InstanceFilterID>052ebb8b-ff13-42c4-aa67-5ef838cbebe5</InstanceFilterID>
      <AttributeID>a7a5ae52-bb1b-4f81-bef5-809595918d3a</AttributeID>
      <AttributeName>Verbosity</AttributeName>
      <UserLevel>0</UserLevel>
      <Visible>true</Visible>
      <Value>0</Value>
      <Blob>1</Blob>
      <Publicity>true</Publicity>
    </InstanzAttribute>
    <InstanzAttribute>
      <InstanzAttributeID>9c746c6f-152c-4ac9-858b-1f274f04e5d0</InstanzAttributeID>
      <InstanzVariantID>ecb8f0e3-5da6-41b7-8abc-6b0fbf3f2aa4</InstanzVariantID>
      <VariantID>7005ffb6-246b-495d-be40-a50fccdf5e91</VariantID>
      <InstanceFilterID>052ebb8b-ff13-42c4-aa67-5ef838cbebe5</InstanceFilterID>
      <AttributeID>897a2345-bd34-429b-9297-3b6c35887fb1</AttributeID>
      <AttributeName>DefaultValue</AttributeName>
      <UserLevel>0</UserLevel>
      <Visible>true</Visible>
      <Value>100</Value>
      <Blob>100</Blob>
      <Publicity>true</Publicity>
    </InstanzAttribute>
    <InstanzAttribute>
      <InstanzAttributeID>154e4d72-9c82-4104-8579-0c09d513d423</InstanzAttributeID>
      <InstanzVariantID>dbf58fde-5bd6-4d53-bb02-47eb5205b0db</InstanzVariantID>
      <VariantID>7bc89cb7-48e0-4c94-9f6a-0f5f7fdbeeba</VariantID>
      <InstanceFilterID>ac995174-05a1-4e42-8867-6c8d814b365c</InstanceFilterID>
      <AttributeID>41766f66-56c2-436c-bf2a-a56ab4a68062</AttributeID>
      <AttributeName>Verbosity</AttributeName>
      <UserLevel>0</UserLevel>
      <Visible>true</Visible>
      <Value>1</Value>
      <Blob>1</Blob>
      <Publicity>true</Publicity>
    </InstanzAttribute>
    <InstanzAttribute>
      <InstanzAttributeID>4cddd2c5-07df-41e6-9504-a2c7a0bcf07d</InstanzAttributeID>
      <InstanzVariantID>dbf58fde-5bd6-4d53-bb02-47eb5205b0db</InstanzVariantID>
      <VariantID>7bc89cb7-48e0-4c94-9f6a-0f5f7fdbeeba</VariantID>
      <InstanceFilterID>ac995174-05a1-4e42-8867-6c8d814b365c</InstanceFilterID>
      <AttributeID>95b2ba6a-b1ea-40cf-a91f-76eb2f0b7064</AttributeID>
      <AttributeName>scalar</AttributeName>
      <UserLevel>0</UserLevel>
      <Visible>true</Visible>
      <Value>0</Value>
      <Blob>1.0</Blob>
      <Publicity>true</Publicity>
    </InstanzAttribute>
    <InstanzAttribute>
      <InstanzAttributeID>ec314d4d-d39f-4bec-8528-2abf61585685</InstanzAttributeID>
      <InstanzVariantID>bb0406fd-3918-46a8-9825-911b22f22f39</InstanzVariantID>
      <VariantID>1d788750-1ba4-457e-b1aa-759b473a236c</VariantID>
      <InstanceFilterID>462ff9ba-2b27-4709-8dba-79b4f58c2f68</InstanceFilterID>
      <AttributeID>1bab875b-3599-4c75-bb75-e3640dfc7c74</AttributeID>
      <AttributeName>Verbosity</AttributeName>
      <UserLevel>0</UserLevel>
      <Visible>true</Visible>
      <Value>0</Value>
      <Blob>1</Blob>
      <Publicity>true</Publicity>
    </InstanzAttribute>
    <InstanzAttribute>
      <InstanzAttributeID>9136509d-6822-4299-90d8-57986572f16e</InstanzAttributeID>
      <InstanzVariantID>bb0406fd-3918-46a8-9825-911b22f22f39</InstanzVariantID>
      <VariantID>1d788750-1ba4-457e-b1aa-759b473a236c</VariantID>
      <InstanceFilterID>462ff9ba-2b27-4709-8dba-79b4f58c2f68</InstanceFilterID>
      <AttributeID>8b47f3a6-bb10-4384-b7de-b1b4cb60e510</AttributeID>
      <AttributeName>ResultType</AttributeName>
      <UserLevel>0</UserLevel>
      <Visible>true</Visible>
      <Value>503</Value>
      <Blob>-1</Blob>
      <Publicity>true</Publicity>
    </InstanzAttribute>
    <InstanzAttribute>
      <InstanzAttributeID>768b3141-b1c2-4f34-901e-40bbdcd7f89c</InstanzAttributeID>
      <InstanzVariantID>18c68746-3327-4732-906d-676ef71b58d3</InstanzVariantID>
      <VariantID>7005ffb6-246b-495d-be40-a50fccdf5e91</VariantID>
      <InstanceFilterID>31f1550f-c4ef-442c-aa7c-b6be9a185068</InstanceFilterID>
      <AttributeID>a7a5ae52-bb1b-4f81-bef5-809595918d3a</AttributeID>
      <AttributeName>Verbosity</AttributeName>
      <UserLevel>0</UserLevel>
      <Visible>true</Visible>
      <Value>1</Value>
      <Blob>1</Blob>
      <Publicity>true</Publicity>
    </InstanzAttribute>
    <InstanzAttribute>
      <InstanzAttributeID>403765e4-1bb3-48de-a9fa-5d7851dffad7</InstanzAttributeID>
      <InstanzVariantID>18c68746-3327-4732-906d-676ef71b58d3</InstanzVariantID>
      <VariantID>7005ffb6-246b-495d-be40-a50fccdf5e91</VariantID>
      <InstanceFilterID>31f1550f-c4ef-442c-aa7c-b6be9a185068</InstanceFilterID>
      <AttributeID>897a2345-bd34-429b-9297-3b6c35887fb1</AttributeID>
      <AttributeName>DefaultValue</AttributeName>
      <UserLevel>0</UserLevel>
      <Visible>true</Visible>
      <Value>100</Value>
      <Blob>100</Blob>
      <Publicity>true</Publicity>
    </InstanzAttribute>
    <InstanzAttribute>
      <InstanzAttributeID>36e4abb8-2841-41a5-97e8-d62bc3faae1a</InstanzAttributeID>
      <InstanzVariantID>18c68746-3327-4732-906d-676ef71b58d3</InstanzVariantID>
      <VariantID>7005ffb6-246b-495d-be40-a50fccdf5e91</VariantID>
      <InstanceFilterID>31f1550f-c4ef-442c-aa7c-b6be9a185068</InstanceFilterID>
      <AttributeID>39e944dd-f2a0-4ae3-8854-f200c4ca8455</AttributeID>
      <AttributeName>sensorid</AttributeName>
      <UserLevel>0</UserLevel>
      <Visible>true</Visible>
      <Value>10001</Value>
      <Blob>10000</Blob>
      <Publicity>true</Publicity>
    </InstanzAttribute>
    <InstanzAttribute>
      <InstanzAttributeID>91883703-07ba-4874-931f-58493a8168de</InstanzAttributeID>
      <InstanzVariantID>1a32995a-aec8-45c6-80a9-d8f0364f00c6</InstanzVariantID>
      <VariantID>52477129-33ee-4bad-a3dc-0b8ac907ebad</VariantID>
      <InstanceFilterID>5d06a3df-c309-4c54-af41-d86da52bbdb6</InstanceFilterID>
      <AttributeID>08bafa5f-38aa-497a-8672-dc25ab83b40c</AttributeID>
      <AttributeName>Verbosity</AttributeName>
      <UserLevel>0</UserLevel>
      <Visible>true</Visible>
      <Value>1</Value>
      <Blob>1</Blob>
      <Publicity>true</Publicity>
    </InstanzAttribute>
    <InstanzAttribute>
      <InstanzAttributeID>e2241a9a-2502-4db7-84d2-612a5c4e14fe</InstanzAttributeID>
      <InstanzVariantID>1a32995a-aec8-45c6-80a9-d8f0364f00c6</InstanzVariantID>
      <VariantID>52477129-33ee-4bad-a3dc-0b8ac907ebad</VariantID>
      <InstanceFilterID>5d06a3df-c309-4c54-af41-d86da52bbdb6</InstanceFilterID>
      <AttributeID>a00bebe3-48d3-47d6-aaff-d75696d2de75</AttributeID>
      <AttributeName>GridSize</AttributeName>
      <UserLevel>0</UserLevel>
      <Visible>true</Visible>
      <Value>1</Value>
      <Blob>1.0</Blob>
      <Publicity>true</Publicity>
    </InstanzAttribute>
    <InstanzAttribute>
      <InstanzAttributeID>417dd2ba-9516-45fe-8e11-da556f0d58b1</InstanzAttributeID>
      <InstanzVariantID>1a32995a-aec8-45c6-80a9-d8f0364f00c6</InstanzVariantID>
      <VariantID>52477129-33ee-4bad-a3dc-0b8ac907ebad</VariantID>
      <InstanceFilterID>5d06a3df-c309-4c54-af41-d86da52bbdb6</InstanceFilterID>
      <AttributeID>27b2b6d7-c056-48e6-93ad-7846fe92b2b6</AttributeID>
      <AttributeName>sensorid</AttributeName>
      <UserLevel>0</UserLevel>
      <Visible>true</Visible>
      <Value>1</Value>
      <Blob>1</Blob>
      <Publicity>true</Publicity>
    </InstanzAttribute>
    <InstanzAttribute>
      <InstanzAttributeID>f0917e4d-d707-45dc-8da3-5acd94b87b28</InstanzAttributeID>
      <InstanzVariantID>cd0e46e2-093b-400a-8047-1b98094976e6</InstanzVariantID>
      <VariantID>1d788750-1ba4-457e-b1aa-759b473a236c</VariantID>
      <InstanceFilterID>617145b9-ec00-4020-bc56-f78cad73e736</InstanceFilterID>
      <AttributeID>8b47f3a6-bb10-4384-b7de-b1b4cb60e510</AttributeID>
      <AttributeName>ResultType</AttributeName>
      <UserLevel>0</UserLevel>
      <Visible>true</Visible>
      <Value>109</Value>
      <Blob>-1</Blob>
      <Publicity>true</Publicity>
    </InstanzAttribute>
    <InstanzAttribute>
      <InstanzAttributeID>e9cba352-3013-4e9f-b920-817d39cba4f0</InstanzAttributeID>
      <InstanzVariantID>cd0e46e2-093b-400a-8047-1b98094976e6</InstanzVariantID>
      <VariantID>1d788750-1ba4-457e-b1aa-759b473a236c</VariantID>
      <InstanceFilterID>617145b9-ec00-4020-bc56-f78cad73e736</InstanceFilterID>
      <AttributeID>1bab875b-3599-4c75-bb75-e3640dfc7c74</AttributeID>
      <AttributeName>Verbosity</AttributeName>
      <UserLevel>0</UserLevel>
      <Visible>true</Visible>
      <Value>0</Value>
      <Blob>1</Blob>
      <Publicity>true</Publicity>
    </InstanzAttribute>
  </InstanzAttributeList>
  <MesswerttypList>
    <messwert>
      <UserTypID>53b41cca-509b-49f4-a099-732f3e159f64</UserTypID>
      <UserTypName>Zaxis pos μm</UserTypName>
      <EnumTyp>509</EnumTyp>
      <OverviewVisibility>false</OverviewVisibility>
      <Plotable>false</Plotable>
      <Savetyp>true</Savetyp>
      <Selectable>false</Selectable>
      <BoundaryPlotable>false</BoundaryPlotable>
      <GlobalBoundaryPlotable>false</GlobalBoundaryPlotable>
      <LineColor>-16777216</LineColor>
      <Max />
      <Min />
      <Unit></Unit>
      <HASSPECIALHWFUNCTION>0</HASSPECIALHWFUNCTION>
      <LISTORDER>1</LISTORDER>
    </messwert>
    <messwert>
      <UserTypID>c18c959e-cdea-4ee6-ae21-6d1d2b003417</UserTypID>
      <UserTypName>Yaxis pos μm</UserTypName>
      <EnumTyp>503</EnumTyp>
      <OverviewVisibility>false</OverviewVisibility>
      <Plotable>false</Plotable>
      <Savetyp>true</Savetyp>
      <Selectable>false</Selectable>
      <BoundaryPlotable>false</BoundaryPlotable>
      <GlobalBoundaryPlotable>false</GlobalBoundaryPlotable>
      <LineColor>-16777216</LineColor>
      <Max />
      <Min />
      <Unit></Unit>
      <HASSPECIALHWFUNCTION>0</HASSPECIALHWFUNCTION>
      <LISTORDER>2</LISTORDER>
    </messwert>
    <messwert>
      <UserTypID>68b4affa-793b-44ad-a39a-d7c808d46a5c</UserTypID>
      <UserTypName></UserTypName>
      <EnumTyp>109</EnumTyp>
      <OverviewVisibility>false</OverviewVisibility>
      <Plotable>false</Plotable>
      <Savetyp>true</Savetyp>
      <Selectable>false</Selectable>
      <BoundaryPlotable>false</BoundaryPlotable>
      <GlobalBoundaryPlotable>false</GlobalBoundaryPlotable>
      <LineColor>-12882427</LineColor>
      <Max />
      <Min />
      <Unit></Unit>
      <HASSPECIALHWFUNCTION>1</HASSPECIALHWFUNCTION>
      <LISTORDER>1</LISTORDER>
    </messwert>
  </MesswerttypList>
  <FehlertypList />
  <SensorTypList>
    <sensor>
      <UserTypID>7309986b-5b21-4d89-943e-bbf1557fa86b</UserTypID>
      <UserTypName></UserTypName>
      <EnumTyp>10027</EnumTyp>
      <OverviewVisibility>true</OverviewVisibility>
      <Plotable>true</Plotable>
      <Savetyp>false</Savetyp>
      <Selectable>true</Selectable>
    </sensor>
    <sensor>
      <UserTypID>124ae91e-623a-480a-bda6-fd619c58b6fd</UserTypID>
      <UserTypName></UserTypName>
      <EnumTyp>10001</EnumTyp>
      <OverviewVisibility>true</OverviewVisibility>
      <Plotable>true</Plotable>
      <Savetyp>false</Savetyp>
      <Selectable>true</Selectable>
    </sensor>
  </SensorTypList>
  <GraphPortList />
  <GraphItemsExtensionList>
    <GraphItemExtension>
      <ItemsExtensionID>985296de-237f-404e-92db-3ba6eb8d2659</ItemsExtensionID>
      <GraphID>3b79c940-8d15-4003-b60c-523db0bea158</GraphID>
      <GraphEditItemID>617145b9-ec00-4020-bc56-f78cad73e736</GraphEditItemID>
      <GraphEditItemType>0</GraphEditItemType>
      <PipeInPortID>f132ea6a-0b0a-48bb-9335-d0a5ff8c31f6</PipeInPortID>
    </GraphItemExtension>
    <GraphItemExtension>
      <ItemsExtensionID>18d365eb-d1f2-4d1f-8abc-4d9653b8bfdd</ItemsExtensionID>
      <GraphID>3b79c940-8d15-4003-b60c-523db0bea158</GraphID>
      <GraphEditItemID>ac995174-05a1-4e42-8867-6c8d814b365c</GraphEditItemID>
      <GraphEditItemType>0</GraphEditItemType>
      <PipeInPortID>f132ea6a-0b0a-48bb-9335-d0a5ff8c31f6</PipeInPortID>
    </GraphItemExtension>
    <GraphItemExtension>
      <ItemsExtensionID>61005259-43fc-4920-89b1-6b4c98b06fb9</ItemsExtensionID>
      <GraphID>3b79c940-8d15-4003-b60c-523db0bea158</GraphID>
      <GraphEditItemID>052ebb8b-ff13-42c4-aa67-5ef838cbebe5</GraphEditItemID>
      <GraphEditItemType>0</GraphEditItemType>
      <PipeInPortID>f132ea6a-0b0a-48bb-9335-d0a5ff8c31f6</PipeInPortID>
    </GraphItemExtension>
    <GraphItemExtension>
      <ItemsExtensionID>849c35b6-92a7-4429-b0c2-825c97495252</ItemsExtensionID>
      <GraphID>3b79c940-8d15-4003-b60c-523db0bea158</GraphID>
      <GraphEditItemID>d42d71fc-74a7-4309-9ff6-ec3df686012e</GraphEditItemID>
      <GraphEditItemType>7</GraphEditItemType>
      <PipeInPortID>f132ea6a-0b0a-48bb-9335-d0a5ff8c31f6</PipeInPortID>
    </GraphItemExtension>
    <GraphItemExtension>
      <ItemsExtensionID>cf68a29a-6141-4e13-be54-85471451e814</ItemsExtensionID>
      <GraphID>3b79c940-8d15-4003-b60c-523db0bea158</GraphID>
      <GraphEditItemID>e72ac443-36ed-4f8a-92a3-4aa1cd7831cb</GraphEditItemID>
      <GraphEditItemType>7</GraphEditItemType>
      <PipeInPortID>f132ea6a-0b0a-48bb-9335-d0a5ff8c31f6</PipeInPortID>
    </GraphItemExtension>
    <GraphItemExtension>
      <ItemsExtensionID>7dc77eed-165e-4af5-9d76-94dd4f02bc43</ItemsExtensionID>
      <GraphID>3b79c940-8d15-4003-b60c-523db0bea158</GraphID>
      <GraphEditItemID>bcf3833f-44a7-425a-9fa6-eb9fcb334cd4</GraphEditItemID>
      <GraphEditItemType>7</GraphEditItemType>
      <PipeInPortID>f132ea6a-0b0a-48bb-9335-d0a5ff8c31f6</PipeInPortID>
    </GraphItemExtension>
    <GraphItemExtension>
      <ItemsExtensionID>e8a4279c-5155-434b-8dd1-a9d8081e5a2d</ItemsExtensionID>
      <GraphID>3b79c940-8d15-4003-b60c-523db0bea158</GraphID>
      <GraphEditItemID>31f1550f-c4ef-442c-aa7c-b6be9a185068</GraphEditItemID>
      <GraphEditItemType>0</GraphEditItemType>
      <PipeInPortID>f132ea6a-0b0a-48bb-9335-d0a5ff8c31f6</PipeInPortID>
    </GraphItemExtension>
    <GraphItemExtension>
      <ItemsExtensionID>98e1f0d2-0a69-47fb-aeb5-cad3a62b667a</ItemsExtensionID>
      <GraphID>3b79c940-8d15-4003-b60c-523db0bea158</GraphID>
      <GraphEditItemID>5d06a3df-c309-4c54-af41-d86da52bbdb6</GraphEditItemID>
      <GraphEditItemType>0</GraphEditItemType>
      <PipeInPortID>f132ea6a-0b0a-48bb-9335-d0a5ff8c31f6</PipeInPortID>
    </GraphItemExtension>
    <GraphItemExtension>
      <ItemsExtensionID>bd959da5-1068-4f1b-bc3e-cb9be6f5ff0c</ItemsExtensionID>
      <GraphID>3b79c940-8d15-4003-b60c-523db0bea158</GraphID>
      <GraphEditItemID>6e96a6fd-d0f4-45e4-a6bd-50d9e597d34e</GraphEditItemID>
      <GraphEditItemType>0</GraphEditItemType>
      <PipeInPortID>f132ea6a-0b0a-48bb-9335-d0a5ff8c31f6</PipeInPortID>
    </GraphItemExtension>
    <GraphItemExtension>
      <ItemsExtensionID>22be179d-8c25-410a-b235-cf57e8f8855c</ItemsExtensionID>
      <GraphID>3b79c940-8d15-4003-b60c-523db0bea158</GraphID>
      <GraphEditItemID>462ff9ba-2b27-4709-8dba-79b4f58c2f68</GraphEditItemID>
      <GraphEditItemType>0</GraphEditItemType>
      <PipeInPortID>f132ea6a-0b0a-48bb-9335-d0a5ff8c31f6</PipeInPortID>
    </GraphItemExtension>
    <GraphItemExtension>
      <ItemsExtensionID>2446c052-3b8a-493e-b3fc-e3f7dff29581</ItemsExtensionID>
      <GraphID>3b79c940-8d15-4003-b60c-523db0bea158</GraphID>
      <GraphEditItemID>a3e9e714-38aa-4fe2-8180-12e0dfa73667</GraphEditItemID>
      <GraphEditItemType>7</GraphEditItemType>
      <PipeInPortID>f132ea6a-0b0a-48bb-9335-d0a5ff8c31f6</PipeInPortID>
    </GraphItemExtension>
  </GraphItemsExtensionList>
</GraphData>